RCC8D/__init__.py
RCC8D/rcc8d.py
RCC8D-0.0.1.dist-info/LICENSE
RCC8D-0.0.1.dist-info/METADATA
RCC8D-0.0.1.dist-info/WHEEL
RCC8D-0.0.1.dist-info/top_level.txt
RCC8D-0.0.1.dist-info/RECORD
