Metadata-Version: 2.1
Name: RCC8D
Version: 0.0.1
Summary: A Python-based implementation of the RCC8D ImageJ/Fiji plugin created by Gabriel Landini and David A Randell.
Author-email: Victoria Porter <vporter03@qub.ac.uk>
Project-URL: Homepage, https://github.com/victoriaporter58/RCC8D
Classifier: Programming Language :: Python :: 3
Classifier: License :: OSI Approved :: GNU General Public License v2 (GPLv2)
Classifier: Operating System :: Microsoft :: Windows
Requires-Python: >=3.10
License-File: LICENSE
Provides-Extra: all
Requires-Dist: opencv-python ; extra == 'all'
Requires-Dist: numpy ; extra == 'all'
